tests/__init__.py
tests/test_time_utility.py
time_utility/__init__.py
time_utility/main.py
time_utility/week.py
time_utility-0.2.1.dist-info/LICENSE
time_utility-0.2.1.dist-info/METADATA
time_utility-0.2.1.dist-info/WHEEL
time_utility-0.2.1.dist-info/top_level.txt
time_utility-0.2.1.dist-info/RECORD
