Metadata-Version: 2.1
Name: time-utility
Version: 0.2.1
Summary: Time utility functions
Home-page: https://github.com/Vieolo/python-time-utility.git
Author: Vieolo OÜ
Author-email: info@vieolo.com
Classifier: Programming Language :: Python :: 3
Classifier: License :: OSI Approved :: MIT License
Classifier: Operating System :: OS Independent
Requires-Python: >=3.10
License-File: LICENSE
